{
  "$schema": "https://yen-gov.github.io/schemas/result.constituency.schema.json",
  "$schema_version": "3.2",
  "sources": [
    {
      "url": "https://www.eci.gov.in/eci-backend/public//all_files/election_report/Jharkhand_Legislative_Assembly_Election__2024_2024/10-Detailed_Results_1744892172.xlsx",
      "fetched_at": "2026-05-12T18:39:40Z"
    },
    {
      "url": "https://www.eci.gov.in/eci-backend/public//all_files/election_report/Jharkhand_Legislative_Assembly_Election__2024_2024/3-List_Of_Political_Parties_Participated_1744890626.xlsx",
      "fetched_at": "2026-05-12T18:39:40Z"
    }
  ],
  "election": "AcGenNov2024",
  "state": "S27",
  "body": "AC",
  "eci_no": 59,
  "constituency_name": "TORPA (ST)",
  "totals": {
    "electors": 199984,
    "votes_polled": 135354,
    "turnout_pct": 67.68
  },
  "candidates": [
    {
      "rank": 1,
      "name": "SUDEEP GUDHIYA",
      "party_short": "JMM",
      "votes": 80887,
      "vote_share_pct": 59.76,
      "is_winner": true
    },
    {
      "rank": 2,
      "name": "KOCHE MUNDA",
      "party_eci_code": "369",
      "party_short": "BJP",
      "votes": 40240,
      "vote_share_pct": 29.73
    },
    {
      "rank": 3,
      "name": "WILSON BHENGRA",
      "party_short": "JLKM",
      "votes": 2832,
      "vote_share_pct": 2.09
    },
    {
      "rank": 4,
      "name": "BRAJENDRA HEMROM",
      "party_short": "IND",
      "votes": 2356,
      "vote_share_pct": 1.74
    },
    {
      "rank": 5,
      "name": "SAVITRI DEVI",
      "party_short": "BSP",
      "votes": 1278,
      "vote_share_pct": 0.94
    }
  ],
  "nota": {
    "votes": 3046,
    "vote_share_pct": 2.25
  },
  "others": {
    "candidate_count": 7,
    "votes": 4715,
    "vote_share_pct": 3.49
  },
  "top_n_cutoff": 5,
  "winner": {
    "name": "SUDEEP GUDHIYA",
    "party_short": "JMM",
    "votes": 80887,
    "margin_votes": 40647,
    "margin_pct": 30.03
  }
}
