{
  "$schema": "https://yen-gov.github.io/schemas/result.constituency.schema.json",
  "$schema_version": "3.2",
  "sources": [],
  "election": "AcGenFeb2017",
  "state": "S24",
  "body": "AC",
  "eci_no": 58,
  "constituency_name": "Dholana",
  "totals": {
    "electors": 379476,
    "votes_polled": 253827,
    "turnout_pct": 66.89
  },
  "candidates": [
    {
      "rank": 1,
      "name": "AAASLAM CHOUDHARY",
      "party_short": "BSP",
      "votes": 88580,
      "vote_share_pct": 34.9,
      "is_winner": true,
      "gender": "M",
      "age": 49,
      "category": "GEN"
    },
    {
      "rank": 2,
      "name": "RAMESH CHAND TOMER",
      "party_short": "BJP",
      "votes": 85004,
      "vote_share_pct": 33.49,
      "gender": "M",
      "age": 68,
      "category": "GEN"
    },
    {
      "rank": 3,
      "name": "DHARMESH SINGH TOMAR",
      "party_short": "SP",
      "votes": 71786,
      "vote_share_pct": 28.28,
      "gender": "M",
      "age": 50,
      "category": "GEN"
    },
    {
      "rank": 4,
      "name": "NAGENDAR SINGH URF NAGAN",
      "party_short": "RLD",
      "votes": 3025,
      "vote_share_pct": 1.19,
      "gender": "M",
      "age": 45,
      "category": "GEN"
    },
    {
      "rank": 5,
      "name": "MUKESH KUMAR",
      "party_short": "SWAJANPA",
      "votes": 2026,
      "vote_share_pct": 0.8,
      "gender": "M",
      "age": 40,
      "category": "SC"
    }
  ],
  "nota": {
    "votes": 1279,
    "vote_share_pct": 0.5
  },
  "others": {
    "candidate_count": 6,
    "votes": 2127,
    "vote_share_pct": 0.83
  },
  "top_n_cutoff": 5,
  "winner": {
    "name": "AAASLAM CHOUDHARY",
    "party_short": "BSP",
    "votes": 88580,
    "margin_votes": 3576,
    "margin_pct": 1.41
  }
}
