{
  "$schema": "https://yen-gov.github.io/schemas/result.constituency.schema.json",
  "$schema_version": "3.2",
  "sources": [],
  "election": "AcGenApr2021",
  "state": "S22",
  "body": "AC",
  "eci_no": 126,
  "constituency_name": "Madathukulam",
  "totals": {
    "electors": 248501,
    "votes_polled": 181902,
    "turnout_pct": 73.2
  },
  "candidates": [
    {
      "rank": 1,
      "name": "C MAHENDRAN",
      "party_short": "ADMK",
      "votes": 84313,
      "vote_share_pct": 46.35,
      "is_winner": true,
      "gender": "M",
      "age": 49,
      "category": "GEN"
    },
    {
      "rank": 2,
      "name": "R.JAYARAMAKRISHNAN",
      "party_short": "DMK",
      "votes": 77875,
      "vote_share_pct": 42.81,
      "gender": "M",
      "age": 53,
      "category": "GEN"
    },
    {
      "rank": 3,
      "name": "C.SHANMUGAVELU",
      "party_short": "AMMKMNKZ",
      "votes": 6515,
      "vote_share_pct": 3.58,
      "gender": "M",
      "age": 71,
      "category": "GEN"
    },
    {
      "rank": 4,
      "name": "U SANUJA",
      "party_short": "NTK",
      "votes": 6245,
      "vote_share_pct": 3.43,
      "gender": "F",
      "age": 37,
      "category": "GEN"
    },
    {
      "rank": 5,
      "name": "K KUMARESAN",
      "party_short": "MNM",
      "votes": 2894,
      "vote_share_pct": 1.59,
      "gender": "M",
      "age": 52,
      "category": "GEN"
    }
  ],
  "nota": {
    "votes": 1048,
    "vote_share_pct": 0.58
  },
  "others": {
    "candidate_count": 10,
    "votes": 3012,
    "vote_share_pct": 1.67
  },
  "top_n_cutoff": 5,
  "winner": {
    "name": "C MAHENDRAN",
    "party_short": "ADMK",
    "votes": 84313,
    "margin_votes": 6438,
    "margin_pct": 3.54
  }
}
