{
  "$schema": "https://yen-gov.github.io/schemas/result.constituency.schema.json",
  "$schema_version": "3.1",
  "sources": [
    {
      "url": "https://www.eci.gov.in/eci-backend/public//all_files/election_report/General_Election_to_the_Legislative_Assembly_of_Tamil_Nadu_2026_2026/10-Detailed_Results_1778165153.xlsx",
      "fetched_at": "2026-05-09T11:59:28Z"
    },
    {
      "url": "https://results.eci.gov.in/ResultAcGenMay2026/partywiseresult-S22.htm",
      "fetched_at": "2026-05-09T11:59:28Z"
    }
  ],
  "election": "AcGenMay2026",
  "state": "S22",
  "body": "AC",
  "eci_no": 128,
  "constituency_name": "ODDANCHATRAM",
  "totals": {
    "electors": 220263,
    "votes_polled": 201624,
    "turnout_pct": 91.54
  },
  "candidates": [
    {
      "rank": 1,
      "name": "Sakkarapani. R",
      "party_eci_code": "582",
      "party_short": "DMK",
      "votes": 93099,
      "vote_share_pct": 46.17,
      "is_winner": true
    },
    {
      "rank": 2,
      "name": "Vidiyal S. Sekar",
      "party_eci_code": "369",
      "party_short": "BJP",
      "votes": 49850,
      "vote_share_pct": 24.72
    },
    {
      "rank": 3,
      "name": "Mohan. S",
      "party_eci_code": "3679",
      "party_short": "TVK",
      "votes": 49155,
      "vote_share_pct": 24.38
    },
    {
      "rank": 4,
      "name": "Ragupathi. P",
      "party_short": "NTK",
      "votes": 5454,
      "vote_share_pct": 2.71
    },
    {
      "rank": 5,
      "name": "Prabaharan. M",
      "party_short": "IND",
      "votes": 646,
      "vote_share_pct": 0.32
    }
  ],
  "nota": {
    "votes": 1491,
    "vote_share_pct": 0.74
  },
  "others": {
    "candidate_count": 9,
    "votes": 1929,
    "vote_share_pct": 0.97
  },
  "top_n_cutoff": 5,
  "winner": {
    "name": "Sakkarapani. R",
    "party_eci_code": "582",
    "party_short": "DMK",
    "votes": 93099,
    "margin_votes": 43249,
    "margin_pct": 21.45
  }
}
