{
  "$schema": "https://yen-gov.github.io/schemas/result.constituency.schema.json",
  "$schema_version": "3.2",
  "sources": [
    {
      "url": "https://www.eci.gov.in/eci-backend/public//all_files/election_report/General_Election_to_the_Legislative_Assembly_of_Tamil_Nadu_2026_2026/10-Detailed_Results_1778165153.xlsx",
      "fetched_at": "2026-05-09T11:59:28Z"
    },
    {
      "url": "https://results.eci.gov.in/ResultAcGenMay2026/partywiseresult-S22.htm",
      "fetched_at": "2026-05-09T11:59:28Z"
    }
  ],
  "election": "AcGenMay2026",
  "state": "S22",
  "body": "AC",
  "eci_no": 149,
  "constituency_name": "ARIYALUR",
  "totals": {
    "electors": 263156,
    "votes_polled": 235858,
    "turnout_pct": 89.63
  },
  "candidates": [
    {
      "rank": 1,
      "name": "Rajendran S",
      "party_eci_code": "75",
      "party_short": "ADMK",
      "votes": 95219,
      "vote_share_pct": 40.37,
      "is_winner": true
    },
    {
      "rank": 2,
      "name": "Latha Balu",
      "party_eci_code": "582",
      "party_short": "DMK",
      "votes": 70721,
      "vote_share_pct": 29.98
    },
    {
      "rank": 3,
      "name": "Sivakumar M",
      "party_eci_code": "3679",
      "party_short": "TVK",
      "votes": 57359,
      "vote_share_pct": 24.32
    },
    {
      "rank": 4,
      "name": "Pugazhendhi D",
      "party_short": "NTK",
      "votes": 8527,
      "vote_share_pct": 3.62
    },
    {
      "rank": 5,
      "name": "Jothibasu K",
      "party_short": "IND",
      "votes": 691,
      "vote_share_pct": 0.29
    }
  ],
  "nota": {
    "votes": 641,
    "vote_share_pct": 0.27
  },
  "others": {
    "candidate_count": 10,
    "votes": 2700,
    "vote_share_pct": 1.15
  },
  "top_n_cutoff": 5,
  "winner": {
    "name": "Rajendran S",
    "party_eci_code": "75",
    "party_short": "ADMK",
    "votes": 95219,
    "margin_votes": 24498,
    "margin_pct": 10.39
  }
}
