{
  "$schema": "https://yen-gov.github.io/schemas/result.constituency.schema.json",
  "$schema_version": "3.1",
  "sources": [
    {
      "url": "https://www.eci.gov.in/eci-backend/public//all_files/election_report/General_Election_to_the_Legislative_Assembly_of_Tamil_Nadu_2026_2026/10-Detailed_Results_1778165153.xlsx",
      "fetched_at": "2026-05-09T11:59:28Z"
    },
    {
      "url": "https://results.eci.gov.in/ResultAcGenMay2026/partywiseresult-S22.htm",
      "fetched_at": "2026-05-09T11:59:28Z"
    }
  ],
  "election": "AcGenMay2026",
  "state": "S22",
  "body": "AC",
  "eci_no": 87,
  "constituency_name": "SANKARI",
  "totals": {
    "electors": 260590,
    "votes_polled": 243779,
    "turnout_pct": 93.55
  },
  "candidates": [
    {
      "rank": 1,
      "name": "Vetrivel. S",
      "party_eci_code": "75",
      "party_short": "ADMK",
      "votes": 87342,
      "vote_share_pct": 35.83,
      "is_winner": true
    },
    {
      "rank": 2,
      "name": "Senthilkumar. K",
      "party_eci_code": "3679",
      "party_short": "TVK",
      "votes": 77825,
      "vote_share_pct": 31.92
    },
    {
      "rank": 3,
      "name": "Manikandan. M",
      "party_eci_code": "582",
      "party_short": "DMK",
      "votes": 65716,
      "vote_share_pct": 26.96
    },
    {
      "rank": 4,
      "name": "Nithya. A",
      "party_short": "NTK",
      "votes": 7534,
      "vote_share_pct": 3.09
    },
    {
      "rank": 5,
      "name": "Dr. Gurunathan. S",
      "party_short": "IDMK",
      "votes": 1009,
      "vote_share_pct": 0.41
    }
  ],
  "nota": {
    "votes": 711,
    "vote_share_pct": 0.29
  },
  "others": {
    "candidate_count": 15,
    "votes": 3642,
    "vote_share_pct": 1.5
  },
  "top_n_cutoff": 5,
  "winner": {
    "name": "Vetrivel. S",
    "party_eci_code": "75",
    "party_short": "ADMK",
    "votes": 87342,
    "margin_votes": 9517,
    "margin_pct": 3.9
  }
}
