{
  "$schema": "https://yen-gov.github.io/schemas/result.constituency.schema.json",
  "$schema_version": "3.1",
  "sources": [
    {
      "url": "https://www.eci.gov.in/eci-backend/public//all_files/election_report/Maharashtra_Legislative_Assembly_Election__2024_2024/10-Detailed_Results_1744893339.xlsx",
      "fetched_at": "2026-05-12T18:39:35Z"
    },
    {
      "url": "https://www.eci.gov.in/eci-backend/public//all_files/election_report/Maharashtra_Legislative_Assembly_Election__2024_2024/3-List_Of_Political_Parties_Participated_1744889410.xlsx",
      "fetched_at": "2026-05-12T18:39:36Z"
    }
  ],
  "election": "AcGenNov2024",
  "state": "S13",
  "body": "AC",
  "eci_no": 108,
  "constituency_name": "AURANGABAD WEST (SC)",
  "totals": {
    "electors": 407238,
    "votes_polled": 248582,
    "turnout_pct": 61.04
  },
  "candidates": [
    {
      "rank": 1,
      "name": "SANJAY PANDURANG SHIRSAT",
      "party_short": "SHS",
      "votes": 122498,
      "vote_share_pct": 49.28,
      "is_winner": true
    },
    {
      "rank": 2,
      "name": "RAJU RAMRAO SHINDE",
      "party_short": "SHSUBT",
      "votes": 106147,
      "vote_share_pct": 42.7
    },
    {
      "rank": 3,
      "name": "ANJAN LAXMAN SALVE",
      "party_short": "VBA",
      "votes": 9667,
      "vote_share_pct": 3.89
    },
    {
      "rank": 4,
      "name": "RAMESH LAXMANRAO GAIKWAD",
      "party_short": "RPI(D)",
      "votes": 2440,
      "vote_share_pct": 0.98
    },
    {
      "rank": 5,
      "name": "KUNAL SURESH LANDGE",
      "party_short": "BSP",
      "votes": 1183,
      "vote_share_pct": 0.48
    }
  ],
  "nota": {
    "votes": 1703,
    "vote_share_pct": 0.69
  },
  "others": {
    "candidate_count": 13,
    "votes": 4944,
    "vote_share_pct": 2.0
  },
  "top_n_cutoff": 5,
  "winner": {
    "name": "SANJAY PANDURANG SHIRSAT",
    "party_short": "SHS",
    "votes": 122498,
    "margin_votes": 16351,
    "margin_pct": 6.58
  }
}
