{
  "$schema": "https://yen-gov.github.io/schemas/result.constituency.schema.json",
  "$schema_version": "3.1",
  "sources": [
    {
      "url": "https://www.eci.gov.in/eci-backend/public//all_files/election_report/General_Election_to_the_Legislative_Assembly_of_West_Bengal_2026_2026/10-Detailed_Results_1778165388.xlsx",
      "fetched_at": "2026-05-09T11:59:36Z"
    },
    {
      "url": "https://results.eci.gov.in/ResultAcGenMay2026/partywiseresult-S25.htm",
      "fetched_at": "2026-05-09T11:59:37Z"
    }
  ],
  "election": "AcGenMay2026",
  "state": "S25",
  "body": "AC",
  "eci_no": 63,
  "constituency_name": "RANINAGAR",
  "totals": {
    "electors": 244547,
    "votes_polled": 237202,
    "turnout_pct": 97.0
  },
  "candidates": [
    {
      "rank": 1,
      "name": "Julfikar Ali",
      "party_eci_code": "742",
      "party_short": "INC",
      "votes": 79423,
      "vote_share_pct": 33.48,
      "is_winner": true
    },
    {
      "rank": 2,
      "name": "Abdul Soumik Hossain",
      "party_eci_code": "140",
      "party_short": "AITC",
      "votes": 76722,
      "vote_share_pct": 32.34
    },
    {
      "rank": 3,
      "name": "Jamal Hossain",
      "party_eci_code": "547",
      "party_short": "CPI(M)",
      "votes": 48587,
      "vote_share_pct": 20.48
    },
    {
      "rank": 4,
      "name": "Ranapratap Singha Roy",
      "party_eci_code": "369",
      "party_short": "BJP",
      "votes": 22728,
      "vote_share_pct": 9.58
    },
    {
      "rank": 5,
      "name": "Yasser Haidar",
      "party_eci_code": "3735",
      "party_short": "AJUP",
      "votes": 2566,
      "vote_share_pct": 1.08
    }
  ],
  "nota": {
    "votes": 2240,
    "vote_share_pct": 0.94
  },
  "others": {
    "candidate_count": 9,
    "votes": 4936,
    "vote_share_pct": 2.08
  },
  "top_n_cutoff": 5,
  "winner": {
    "name": "Julfikar Ali",
    "party_eci_code": "742",
    "party_short": "INC",
    "votes": 79423,
    "margin_votes": 2701,
    "margin_pct": 1.14
  }
}
