{
  "$schema": "https://yen-gov.github.io/schemas/result.constituency.schema.json",
  "$schema_version": "3.2",
  "sources": [],
  "election": "AcGenFeb2022",
  "state": "S24",
  "body": "AC",
  "eci_no": 165,
  "constituency_name": "Unnao",
  "totals": {
    "electors": 409927,
    "votes_polled": 245372,
    "turnout_pct": 59.86
  },
  "candidates": [
    {
      "rank": 1,
      "name": "Pankaj Gupta",
      "party_short": "BJP",
      "votes": 126670,
      "vote_share_pct": 51.62,
      "is_winner": true,
      "gender": "M",
      "age": 52,
      "category": "GEN"
    },
    {
      "rank": 2,
      "name": "Abhinav Kumar",
      "party_short": "SP",
      "votes": 95542,
      "vote_share_pct": 38.94,
      "gender": "M",
      "age": 31,
      "category": "GEN"
    },
    {
      "rank": 3,
      "name": "Devendra Singh",
      "party_short": "BSP",
      "votes": 15605,
      "vote_share_pct": 6.36,
      "gender": "M",
      "age": 44,
      "category": "GEN"
    },
    {
      "rank": 4,
      "name": "Tanmay Srivastava",
      "party_short": "RVLP",
      "votes": 2190,
      "vote_share_pct": 0.89,
      "gender": "M",
      "age": 28,
      "category": "GEN"
    },
    {
      "rank": 5,
      "name": "Asha Singh",
      "party_short": "INC",
      "votes": 1555,
      "vote_share_pct": 0.63,
      "gender": "F",
      "age": 45,
      "category": "GEN"
    }
  ],
  "nota": {
    "votes": 1425,
    "vote_share_pct": 0.58
  },
  "others": {
    "candidate_count": 5,
    "votes": 2385,
    "vote_share_pct": 0.98
  },
  "top_n_cutoff": 5,
  "winner": {
    "name": "Pankaj Gupta",
    "party_short": "BJP",
    "votes": 126670,
    "margin_votes": 31128,
    "margin_pct": 12.69
  }
}
