{
  "$schema": "https://yen-gov.github.io/schemas/result.constituency.schema.json",
  "$schema_version": "3.2",
  "sources": [],
  "election": "AcGenMay2018",
  "state": "S10",
  "body": "AC",
  "eci_no": 139,
  "constituency_name": "Gauribidanur",
  "totals": {
    "electors": 203048,
    "votes_polled": 168670,
    "turnout_pct": 83.06902801308064
  },
  "candidates": [
    {
      "rank": 1,
      "name": "N.H.SHIVASHANKARA REDDY",
      "party_short": "INC",
      "votes": 69000,
      "vote_share_pct": 40.90828244501097,
      "is_winner": true,
      "gender": "M",
      "age": 64,
      "category": "GEN"
    },
    {
      "rank": 2,
      "name": "C.R.NARASIMHAMURTHY",
      "party_short": "JD(S)",
      "votes": 59832,
      "vote_share_pct": 35.47281674275212,
      "gender": "M",
      "age": 52,
      "category": "GEN"
    },
    {
      "rank": 3,
      "name": "K.JAIPAL REDDY",
      "party_short": "BJP",
      "votes": 34759,
      "vote_share_pct": 20.60769550008893,
      "gender": "M",
      "age": 40,
      "category": "GEN"
    },
    {
      "rank": 4,
      "name": "N.R.RAVICHANDRAREDDY",
      "party_short": "CPM",
      "votes": 1095,
      "vote_share_pct": 0.6491966561925654,
      "gender": "M",
      "age": 48,
      "category": "GEN"
    },
    {
      "rank": 5,
      "name": "ANANTHA.G. (P.T.MASTER)",
      "party_short": "RPI(A)",
      "votes": 731,
      "vote_share_pct": 0.43339064445366693,
      "gender": "M",
      "age": 57,
      "category": "SC"
    }
  ],
  "nota": {
    "votes": 784,
    "vote_share_pct": 0.4648129483607044
  },
  "others": {
    "candidate_count": 8,
    "votes": 2469,
    "vote_share_pct": 1.46
  },
  "top_n_cutoff": 5,
  "winner": {
    "name": "N.H.SHIVASHANKARA REDDY",
    "party_short": "INC",
    "votes": 69000,
    "margin_votes": 9168,
    "margin_pct": 5.44
  }
}
